{
  "paper": "P2",
  "phase": "E2-T3",
  "method": "import_candidate_labels",
  "game": "asteroids",
  "frame": null,
  "state": null,
  "target_output": "ram_to_concept_candidate_map",
  "metric_name": "n_candidate_labels",
  "value": 66,
  "ci": null,
  "stderr": null,
  "n": 66,
  "seed": null,
  "where": "local",
  "commit": "a6514d51",
  "oracle_ref": null,
  "timestamp": "2026-07-02T17:32:58.505177+00:00",
  "sources": {
    "AtariARI": {
      "available": true,
      "ref": "mila-iqia/atari-representation-learning (AtariARI; Anand et al. NeurIPS 2019), atariari/benchmark/ram_annotations.py :: atari_dict",
      "n": 10,
      "offset_corrected": false
    },
    "OCAtari": {
      "available": true,
      "ref": "OCAtari (Delfosse et al. 2024), ocatari/ram/<game>.py RAM-mode extractors",
      "src_dir": "jaxtari/.venv/lib/python3.13/site-packages/ocatari",
      "module": "ram/asteroids.py",
      "n": 56,
      "offset_corrected": true
    }
  },
  "ram_space": {
    "size_bytes": 128,
    "base_addr": "0x80"
  },
  "status": "candidate_correlational",
  "verify_with": "P2-E2-2 (perturb byte -> object moves on exact framebuffer)",
  "candidates": [
    {
      "concept": "num_lives_direction",
      "ram_index": 60,
      "ram_addr_hex": "0xBC",
      "offset": null,
      "offset_applied": false,
      "raw": true,
      "source": "AtariARI",
      "source_ref": "mila-iqia/atari-representation-learning (AtariARI; Anand et al. NeurIPS 2019), atariari/benchmark/ram_annotations.py :: atari_dict",
      "verified": false,
      "note": "raw RAM index; not aligned to rendered framebuffer position"
    },
    {
      "concept": "player_score_high",
      "ram_index": 61,
      "ram_addr_hex": "0xBD",
      "offset": null,
      "offset_applied": false,
      "raw": true,
      "source": "AtariARI",
      "source_ref": "mila-iqia/atari-representation-learning (AtariARI; Anand et al. NeurIPS 2019), atariari/benchmark/ram_annotations.py :: atari_dict",
      "verified": false,
      "note": "raw RAM index; not aligned to rendered framebuffer position"
    },
    {
      "concept": "player_score_low",
      "ram_index": 62,
      "ram_addr_hex": "0xBE",
      "offset": null,
      "offset_applied": false,
      "raw": true,
      "source": "AtariARI",
      "source_ref": "mila-iqia/atari-representation-learning (AtariARI; Anand et al. NeurIPS 2019), atariari/benchmark/ram_annotations.py :: atari_dict",
      "verified": false,
      "note": "raw RAM index; not aligned to rendered framebuffer position"
    },
    {
      "concept": "player_x",
      "ram_index": 73,
      "ram_addr_hex": "0xC9",
      "offset": null,
      "offset_applied": false,
      "raw": true,
      "source": "AtariARI",
      "source_ref": "mila-iqia/atari-representation-learning (AtariARI; Anand et al. NeurIPS 2019), atariari/benchmark/ram_annotations.py :: atari_dict",
      "verified": false,
      "note": "raw RAM index; not aligned to rendered framebuffer position"
    },
    {
      "concept": "player_y",
      "ram_index": 74,
      "ram_addr_hex": "0xCA",
      "offset": null,
      "offset_applied": false,
      "raw": true,
      "source": "AtariARI",
      "source_ref": "mila-iqia/atari-representation-learning (AtariARI; Anand et al. NeurIPS 2019), atariari/benchmark/ram_annotations.py :: atari_dict",
      "verified": false,
      "note": "raw RAM index; not aligned to rendered framebuffer position"
    },
    {
      "concept": "player_missile_x1",
      "ram_index": 83,
      "ram_addr_hex": "0xD3",
      "offset": null,
      "offset_applied": false,
      "raw": true,
      "source": "AtariARI",
      "source_ref": "mila-iqia/atari-representation-learning (AtariARI; Anand et al. NeurIPS 2019), atariari/benchmark/ram_annotations.py :: atari_dict",
      "verified": false,
      "note": "raw RAM index; not aligned to rendered framebuffer position"
    },
    {
      "concept": "player_missile_x2",
      "ram_index": 84,
      "ram_addr_hex": "0xD4",
      "offset": null,
      "offset_applied": false,
      "raw": true,
      "source": "AtariARI",
      "source_ref": "mila-iqia/atari-representation-learning (AtariARI; Anand et al. NeurIPS 2019), atariari/benchmark/ram_annotations.py :: atari_dict",
      "verified": false,
      "note": "raw RAM index; not aligned to rendered framebuffer position"
    },
    {
      "concept": "player_missile_y1",
      "ram_index": 86,
      "ram_addr_hex": "0xD6",
      "offset": null,
      "offset_applied": false,
      "raw": true,
      "source": "AtariARI",
      "source_ref": "mila-iqia/atari-representation-learning (AtariARI; Anand et al. NeurIPS 2019), atariari/benchmark/ram_annotations.py :: atari_dict",
      "verified": false,
      "note": "raw RAM index; not aligned to rendered framebuffer position"
    },
    {
      "concept": "player_missile_y2",
      "ram_index": 87,
      "ram_addr_hex": "0xD7",
      "offset": null,
      "offset_applied": false,
      "raw": true,
      "source": "AtariARI",
      "source_ref": "mila-iqia/atari-representation-learning (AtariARI; Anand et al. NeurIPS 2019), atariari/benchmark/ram_annotations.py :: atari_dict",
      "verified": false,
      "note": "raw RAM index; not aligned to rendered framebuffer position"
    },
    {
      "concept": "player_missile_direction",
      "ram_index": 89,
      "ram_addr_hex": "0xD9",
      "offset": null,
      "offset_applied": false,
      "raw": true,
      "source": "AtariARI",
      "source_ref": "mila-iqia/atari-representation-learning (AtariARI; Anand et al. NeurIPS 2019), atariari/benchmark/ram_annotations.py :: atari_dict",
      "verified": false,
      "note": "raw RAM index; not aligned to rendered framebuffer position"
    },
    {
      "concept": "asteroid_1",
      "ram_index": 3,
      "ram_addr_hex": "0x83",
      "offset": null,
      "offset_applied": false,
      "raw": true,
      "is_slice": false,
      "slice_end": null,
      "source": "OCAtari",
      "source_ref": "OCAtari (Delfosse et al. 2024), ocatari/ram/<game>.py RAM-mode extractors",
      "extractor_func": "_detect_objects_asteroids_raw",
      "verified": false,
      "note": "RAM-mode extractor reference (no additive offset at use site)"
    },
    {
      "concept": "asteroid_2",
      "ram_index": 4,
      "ram_addr_hex": "0x84",
      "offset": null,
      "offset_applied": false,
      "raw": true,
      "is_slice": false,
      "slice_end": null,
      "source": "OCAtari",
      "source_ref": "OCAtari (Delfosse et al. 2024), ocatari/ram/<game>.py RAM-mode extractors",
      "extractor_func": "_detect_objects_asteroids_raw",
      "verified": false,
      "note": "RAM-mode extractor reference (no additive offset at use site)"
    },
    {
      "concept": "asteroid_3",
      "ram_index": 5,
      "ram_addr_hex": "0x85",
      "offset": null,
      "offset_applied": false,
      "raw": true,
      "is_slice": false,
      "slice_end": null,
      "source": "OCAtari",
      "source_ref": "OCAtari (Delfosse et al. 2024), ocatari/ram/<game>.py RAM-mode extractors",
      "extractor_func": "_detect_objects_asteroids_raw",
      "verified": false,
      "note": "RAM-mode extractor reference (no additive offset at use site)"
    },
    {
      "concept": "asteroid_4",
      "ram_index": 6,
      "ram_addr_hex": "0x86",
      "offset": null,
      "offset_applied": false,
      "raw": true,
      "is_slice": false,
      "slice_end": null,
      "source": "OCAtari",
      "source_ref": "OCAtari (Delfosse et al. 2024), ocatari/ram/<game>.py RAM-mode extractors",
      "extractor_func": "_detect_objects_asteroids_raw",
      "verified": false,
      "note": "RAM-mode extractor reference (no additive offset at use site)"
    },
    {
      "concept": "asteroid_5",
      "ram_index": 7,
      "ram_addr_hex": "0x87",
      "offset": null,
      "offset_applied": false,
      "raw": true,
      "is_slice": false,
      "slice_end": null,
      "source": "OCAtari",
      "source_ref": "OCAtari (Delfosse et al. 2024), ocatari/ram/<game>.py RAM-mode extractors",
      "extractor_func": "_detect_objects_asteroids_raw",
      "verified": false,
      "note": "RAM-mode extractor reference (no additive offset at use site)"
    },
    {
      "concept": "asteroid_6",
      "ram_index": 8,
      "ram_addr_hex": "0x88",
      "offset": null,
      "offset_applied": false,
      "raw": true,
      "is_slice": false,
      "slice_end": null,
      "source": "OCAtari",
      "source_ref": "OCAtari (Delfosse et al. 2024), ocatari/ram/<game>.py RAM-mode extractors",
      "extractor_func": "_detect_objects_asteroids_raw",
      "verified": false,
      "note": "RAM-mode extractor reference (no additive offset at use site)"
    },
    {
      "concept": "asteroid_7",
      "ram_index": 9,
      "ram_addr_hex": "0x89",
      "offset": null,
      "offset_applied": false,
      "raw": true,
      "is_slice": false,
      "slice_end": null,
      "source": "OCAtari",
      "source_ref": "OCAtari (Delfosse et al. 2024), ocatari/ram/<game>.py RAM-mode extractors",
      "extractor_func": "_detect_objects_asteroids_raw",
      "verified": false,
      "note": "RAM-mode extractor reference (no additive offset at use site)"
    },
    {
      "concept": "asteroid_8",
      "ram_index": 10,
      "ram_addr_hex": "0x8A",
      "offset": null,
      "offset_applied": false,
      "raw": true,
      "is_slice": false,
      "slice_end": null,
      "source": "OCAtari",
      "source_ref": "OCAtari (Delfosse et al. 2024), ocatari/ram/<game>.py RAM-mode extractors",
      "extractor_func": "_detect_objects_asteroids_raw",
      "verified": false,
      "note": "RAM-mode extractor reference (no additive offset at use site)"
    },
    {
      "concept": "asteroid_9",
      "ram_index": 11,
      "ram_addr_hex": "0x8B",
      "offset": null,
      "offset_applied": false,
      "raw": true,
      "is_slice": false,
      "slice_end": null,
      "source": "OCAtari",
      "source_ref": "OCAtari (Delfosse et al. 2024), ocatari/ram/<game>.py RAM-mode extractors",
      "extractor_func": "_detect_objects_asteroids_raw",
      "verified": false,
      "note": "RAM-mode extractor reference (no additive offset at use site)"
    },
    {
      "concept": "asteroid_10",
      "ram_index": 12,
      "ram_addr_hex": "0x8C",
      "offset": null,
      "offset_applied": false,
      "raw": true,
      "is_slice": false,
      "slice_end": null,
      "source": "OCAtari",
      "source_ref": "OCAtari (Delfosse et al. 2024), ocatari/ram/<game>.py RAM-mode extractors",
      "extractor_func": "_detect_objects_asteroids_raw",
      "verified": false,
      "note": "RAM-mode extractor reference (no additive offset at use site)"
    },
    {
      "concept": "asteroid_11",
      "ram_index": 13,
      "ram_addr_hex": "0x8D",
      "offset": null,
      "offset_applied": false,
      "raw": true,
      "is_slice": false,
      "slice_end": null,
      "source": "OCAtari",
      "source_ref": "OCAtari (Delfosse et al. 2024), ocatari/ram/<game>.py RAM-mode extractors",
      "extractor_func": "_detect_objects_asteroids_raw",
      "verified": false,
      "note": "RAM-mode extractor reference (no additive offset at use site)"
    },
    {
      "concept": "asteroid_12",
      "ram_index": 14,
      "ram_addr_hex": "0x8E",
      "offset": null,
      "offset_applied": false,
      "raw": true,
      "is_slice": false,
      "slice_end": null,
      "source": "OCAtari",
      "source_ref": "OCAtari (Delfosse et al. 2024), ocatari/ram/<game>.py RAM-mode extractors",
      "extractor_func": "_detect_objects_asteroids_raw",
      "verified": false,
      "note": "RAM-mode extractor reference (no additive offset at use site)"
    },
    {
      "concept": "asteroid_13",
      "ram_index": 15,
      "ram_addr_hex": "0x8F",
      "offset": null,
      "offset_applied": false,
      "raw": true,
      "is_slice": false,
      "slice_end": null,
      "source": "OCAtari",
      "source_ref": "OCAtari (Delfosse et al. 2024), ocatari/ram/<game>.py RAM-mode extractors",
      "extractor_func": "_detect_objects_asteroids_raw",
      "verified": false,
      "note": "RAM-mode extractor reference (no additive offset at use site)"
    },
    {
      "concept": "asteroid_14",
      "ram_index": 16,
      "ram_addr_hex": "0x90",
      "offset": null,
      "offset_applied": false,
      "raw": true,
      "is_slice": false,
      "slice_end": null,
      "source": "OCAtari",
      "source_ref": "OCAtari (Delfosse et al. 2024), ocatari/ram/<game>.py RAM-mode extractors",
      "extractor_func": "_detect_objects_asteroids_raw",
      "verified": false,
      "note": "RAM-mode extractor reference (no additive offset at use site)"
    },
    {
      "concept": "asteroid_15",
      "ram_index": 17,
      "ram_addr_hex": "0x91",
      "offset": null,
      "offset_applied": false,
      "raw": true,
      "is_slice": false,
      "slice_end": null,
      "source": "OCAtari",
      "source_ref": "OCAtari (Delfosse et al. 2024), ocatari/ram/<game>.py RAM-mode extractors",
      "extractor_func": "_detect_objects_asteroids_raw",
      "verified": false,
      "note": "RAM-mode extractor reference (no additive offset at use site)"
    },
    {
      "concept": "asteroid_16",
      "ram_index": 18,
      "ram_addr_hex": "0x92",
      "offset": null,
      "offset_applied": false,
      "raw": true,
      "is_slice": false,
      "slice_end": null,
      "source": "OCAtari",
      "source_ref": "OCAtari (Delfosse et al. 2024), ocatari/ram/<game>.py RAM-mode extractors",
      "extractor_func": "_detect_objects_asteroids_raw",
      "verified": false,
      "note": "RAM-mode extractor reference (no additive offset at use site)"
    },
    {
      "concept": "asteroid_17",
      "ram_index": 19,
      "ram_addr_hex": "0x93",
      "offset": null,
      "offset_applied": false,
      "raw": true,
      "is_slice": false,
      "slice_end": null,
      "source": "OCAtari",
      "source_ref": "OCAtari (Delfosse et al. 2024), ocatari/ram/<game>.py RAM-mode extractors",
      "extractor_func": "_detect_objects_asteroids_raw",
      "verified": false,
      "note": "RAM-mode extractor reference (no additive offset at use site)"
    },
    {
      "concept": "asteroid_1",
      "ram_index": 21,
      "ram_addr_hex": "0x95",
      "offset": null,
      "offset_applied": false,
      "raw": true,
      "is_slice": false,
      "slice_end": null,
      "source": "OCAtari",
      "source_ref": "OCAtari (Delfosse et al. 2024), ocatari/ram/<game>.py RAM-mode extractors",
      "extractor_func": "_detect_objects_asteroids_raw",
      "verified": false,
      "note": "RAM-mode extractor reference (no additive offset at use site)"
    },
    {
      "concept": "asteroid_2",
      "ram_index": 22,
      "ram_addr_hex": "0x96",
      "offset": null,
      "offset_applied": false,
      "raw": true,
      "is_slice": false,
      "slice_end": null,
      "source": "OCAtari",
      "source_ref": "OCAtari (Delfosse et al. 2024), ocatari/ram/<game>.py RAM-mode extractors",
      "extractor_func": "_detect_objects_asteroids_raw",
      "verified": false,
      "note": "RAM-mode extractor reference (no additive offset at use site)"
    },
    {
      "concept": "asteroid_3",
      "ram_index": 23,
      "ram_addr_hex": "0x97",
      "offset": null,
      "offset_applied": false,
      "raw": true,
      "is_slice": false,
      "slice_end": null,
      "source": "OCAtari",
      "source_ref": "OCAtari (Delfosse et al. 2024), ocatari/ram/<game>.py RAM-mode extractors",
      "extractor_func": "_detect_objects_asteroids_raw",
      "verified": false,
      "note": "RAM-mode extractor reference (no additive offset at use site)"
    },
    {
      "concept": "asteroid_4",
      "ram_index": 24,
      "ram_addr_hex": "0x98",
      "offset": null,
      "offset_applied": false,
      "raw": true,
      "is_slice": false,
      "slice_end": null,
      "source": "OCAtari",
      "source_ref": "OCAtari (Delfosse et al. 2024), ocatari/ram/<game>.py RAM-mode extractors",
      "extractor_func": "_detect_objects_asteroids_raw",
      "verified": false,
      "note": "RAM-mode extractor reference (no additive offset at use site)"
    },
    {
      "concept": "asteroid_5",
      "ram_index": 25,
      "ram_addr_hex": "0x99",
      "offset": null,
      "offset_applied": false,
      "raw": true,
      "is_slice": false,
      "slice_end": null,
      "source": "OCAtari",
      "source_ref": "OCAtari (Delfosse et al. 2024), ocatari/ram/<game>.py RAM-mode extractors",
      "extractor_func": "_detect_objects_asteroids_raw",
      "verified": false,
      "note": "RAM-mode extractor reference (no additive offset at use site)"
    },
    {
      "concept": "asteroid_6",
      "ram_index": 26,
      "ram_addr_hex": "0x9A",
      "offset": null,
      "offset_applied": false,
      "raw": true,
      "is_slice": false,
      "slice_end": null,
      "source": "OCAtari",
      "source_ref": "OCAtari (Delfosse et al. 2024), ocatari/ram/<game>.py RAM-mode extractors",
      "extractor_func": "_detect_objects_asteroids_raw",
      "verified": false,
      "note": "RAM-mode extractor reference (no additive offset at use site)"
    },
    {
      "concept": "asteroid_7",
      "ram_index": 27,
      "ram_addr_hex": "0x9B",
      "offset": null,
      "offset_applied": false,
      "raw": true,
      "is_slice": false,
      "slice_end": null,
      "source": "OCAtari",
      "source_ref": "OCAtari (Delfosse et al. 2024), ocatari/ram/<game>.py RAM-mode extractors",
      "extractor_func": "_detect_objects_asteroids_raw",
      "verified": false,
      "note": "RAM-mode extractor reference (no additive offset at use site)"
    },
    {
      "concept": "asteroid_8",
      "ram_index": 28,
      "ram_addr_hex": "0x9C",
      "offset": null,
      "offset_applied": false,
      "raw": true,
      "is_slice": false,
      "slice_end": null,
      "source": "OCAtari",
      "source_ref": "OCAtari (Delfosse et al. 2024), ocatari/ram/<game>.py RAM-mode extractors",
      "extractor_func": "_detect_objects_asteroids_raw",
      "verified": false,
      "note": "RAM-mode extractor reference (no additive offset at use site)"
    },
    {
      "concept": "asteroid_9",
      "ram_index": 29,
      "ram_addr_hex": "0x9D",
      "offset": null,
      "offset_applied": false,
      "raw": true,
      "is_slice": false,
      "slice_end": null,
      "source": "OCAtari",
      "source_ref": "OCAtari (Delfosse et al. 2024), ocatari/ram/<game>.py RAM-mode extractors",
      "extractor_func": "_detect_objects_asteroids_raw",
      "verified": false,
      "note": "RAM-mode extractor reference (no additive offset at use site)"
    },
    {
      "concept": "asteroid_10",
      "ram_index": 30,
      "ram_addr_hex": "0x9E",
      "offset": null,
      "offset_applied": false,
      "raw": true,
      "is_slice": false,
      "slice_end": null,
      "source": "OCAtari",
      "source_ref": "OCAtari (Delfosse et al. 2024), ocatari/ram/<game>.py RAM-mode extractors",
      "extractor_func": "_detect_objects_asteroids_raw",
      "verified": false,
      "note": "RAM-mode extractor reference (no additive offset at use site)"
    },
    {
      "concept": "asteroid_11",
      "ram_index": 31,
      "ram_addr_hex": "0x9F",
      "offset": null,
      "offset_applied": false,
      "raw": true,
      "is_slice": false,
      "slice_end": null,
      "source": "OCAtari",
      "source_ref": "OCAtari (Delfosse et al. 2024), ocatari/ram/<game>.py RAM-mode extractors",
      "extractor_func": "_detect_objects_asteroids_raw",
      "verified": false,
      "note": "RAM-mode extractor reference (no additive offset at use site)"
    },
    {
      "concept": "asteroid_12",
      "ram_index": 32,
      "ram_addr_hex": "0xA0",
      "offset": null,
      "offset_applied": false,
      "raw": true,
      "is_slice": false,
      "slice_end": null,
      "source": "OCAtari",
      "source_ref": "OCAtari (Delfosse et al. 2024), ocatari/ram/<game>.py RAM-mode extractors",
      "extractor_func": "_detect_objects_asteroids_raw",
      "verified": false,
      "note": "RAM-mode extractor reference (no additive offset at use site)"
    },
    {
      "concept": "asteroid_13",
      "ram_index": 33,
      "ram_addr_hex": "0xA1",
      "offset": null,
      "offset_applied": false,
      "raw": true,
      "is_slice": false,
      "slice_end": null,
      "source": "OCAtari",
      "source_ref": "OCAtari (Delfosse et al. 2024), ocatari/ram/<game>.py RAM-mode extractors",
      "extractor_func": "_detect_objects_asteroids_raw",
      "verified": false,
      "note": "RAM-mode extractor reference (no additive offset at use site)"
    },
    {
      "concept": "asteroid_14",
      "ram_index": 34,
      "ram_addr_hex": "0xA2",
      "offset": null,
      "offset_applied": false,
      "raw": true,
      "is_slice": false,
      "slice_end": null,
      "source": "OCAtari",
      "source_ref": "OCAtari (Delfosse et al. 2024), ocatari/ram/<game>.py RAM-mode extractors",
      "extractor_func": "_detect_objects_asteroids_raw",
      "verified": false,
      "note": "RAM-mode extractor reference (no additive offset at use site)"
    },
    {
      "concept": "asteroid_15",
      "ram_index": 35,
      "ram_addr_hex": "0xA3",
      "offset": null,
      "offset_applied": false,
      "raw": true,
      "is_slice": false,
      "slice_end": null,
      "source": "OCAtari",
      "source_ref": "OCAtari (Delfosse et al. 2024), ocatari/ram/<game>.py RAM-mode extractors",
      "extractor_func": "_detect_objects_asteroids_raw",
      "verified": false,
      "note": "RAM-mode extractor reference (no additive offset at use site)"
    },
    {
      "concept": "asteroid_16",
      "ram_index": 36,
      "ram_addr_hex": "0xA4",
      "offset": null,
      "offset_applied": false,
      "raw": true,
      "is_slice": false,
      "slice_end": null,
      "source": "OCAtari",
      "source_ref": "OCAtari (Delfosse et al. 2024), ocatari/ram/<game>.py RAM-mode extractors",
      "extractor_func": "_detect_objects_asteroids_raw",
      "verified": false,
      "note": "RAM-mode extractor reference (no additive offset at use site)"
    },
    {
      "concept": "asteroid_17",
      "ram_index": 37,
      "ram_addr_hex": "0xA5",
      "offset": null,
      "offset_applied": false,
      "raw": true,
      "is_slice": false,
      "slice_end": null,
      "source": "OCAtari",
      "source_ref": "OCAtari (Delfosse et al. 2024), ocatari/ram/<game>.py RAM-mode extractors",
      "extractor_func": "_detect_objects_asteroids_raw",
      "verified": false,
      "note": "RAM-mode extractor reference (no additive offset at use site)"
    },
    {
      "concept": "asteroid_variation",
      "ram_index": 39,
      "ram_addr_hex": "0xA7",
      "offset": null,
      "offset_applied": false,
      "raw": true,
      "is_slice": true,
      "slice_end": 57,
      "source": "OCAtari",
      "source_ref": "OCAtari (Delfosse et al. 2024), ocatari/ram/<game>.py RAM-mode extractors",
      "extractor_func": "_detect_objects_asteroids_raw",
      "verified": false,
      "note": "RAM-mode extractor reference (no additive offset at use site)"
    },
    {
      "concept": "player.orientation",
      "ram_index": 60,
      "ram_addr_hex": "0xBC",
      "offset": null,
      "offset_applied": false,
      "raw": true,
      "is_slice": false,
      "slice_end": null,
      "source": "OCAtari",
      "source_ref": "OCAtari (Delfosse et al. 2024), ocatari/ram/<game>.py RAM-mode extractors",
      "extractor_func": "update_player",
      "verified": false,
      "note": "RAM-mode extractor reference (no additive offset at use site)"
    },
    {
      "concept": "player.wh",
      "ram_index": 60,
      "ram_addr_hex": "0xBC",
      "offset": null,
      "offset_applied": false,
      "raw": true,
      "is_slice": false,
      "slice_end": null,
      "source": "OCAtari",
      "source_ref": "OCAtari (Delfosse et al. 2024), ocatari/ram/<game>.py RAM-mode extractors",
      "extractor_func": "update_player",
      "verified": false,
      "note": "RAM-mode extractor reference (no additive offset at use site)"
    },
    {
      "concept": "player.xy",
      "ram_index": 60,
      "ram_addr_hex": "0xBC",
      "offset": null,
      "offset_applied": false,
      "raw": true,
      "is_slice": false,
      "slice_end": null,
      "source": "OCAtari",
      "source_ref": "OCAtari (Delfosse et al. 2024), ocatari/ram/<game>.py RAM-mode extractors",
      "extractor_func": "update_player",
      "verified": false,
      "note": "RAM-mode extractor reference (no additive offset at use site)"
    },
    {
      "concept": "player_direction",
      "ram_index": 60,
      "ram_addr_hex": "0xBC",
      "offset": null,
      "offset_applied": false,
      "raw": true,
      "is_slice": false,
      "slice_end": null,
      "source": "OCAtari",
      "source_ref": "OCAtari (Delfosse et al. 2024), ocatari/ram/<game>.py RAM-mode extractors",
      "extractor_func": "_detect_objects_asteroids_raw",
      "verified": false,
      "note": "RAM-mode extractor reference (no additive offset at use site)"
    },
    {
      "concept": "score",
      "ram_index": 61,
      "ram_addr_hex": "0xBD",
      "offset": null,
      "offset_applied": false,
      "raw": true,
      "is_slice": false,
      "slice_end": null,
      "source": "OCAtari",
      "source_ref": "OCAtari (Delfosse et al. 2024), ocatari/ram/<game>.py RAM-mode extractors",
      "extractor_func": "_augment_info_asteroids_ram",
      "verified": false,
      "note": "RAM-mode extractor reference (no additive offset at use site)"
    },
    {
      "concept": "score_high",
      "ram_index": 61,
      "ram_addr_hex": "0xBD",
      "offset": null,
      "offset_applied": false,
      "raw": true,
      "is_slice": false,
      "slice_end": null,
      "source": "OCAtari",
      "source_ref": "OCAtari (Delfosse et al. 2024), ocatari/ram/<game>.py RAM-mode extractors",
      "extractor_func": "_detect_objects_asteroids_raw",
      "verified": false,
      "note": "RAM-mode extractor reference (no additive offset at use site)"
    },
    {
      "concept": "score",
      "ram_index": 62,
      "ram_addr_hex": "0xBE",
      "offset": null,
      "offset_applied": false,
      "raw": true,
      "is_slice": false,
      "slice_end": null,
      "source": "OCAtari",
      "source_ref": "OCAtari (Delfosse et al. 2024), ocatari/ram/<game>.py RAM-mode extractors",
      "extractor_func": "_augment_info_asteroids_ram",
      "verified": false,
      "note": "RAM-mode extractor reference (no additive offset at use site)"
    },
    {
      "concept": "score_low",
      "ram_index": 62,
      "ram_addr_hex": "0xBE",
      "offset": null,
      "offset_applied": false,
      "raw": true,
      "is_slice": false,
      "slice_end": null,
      "source": "OCAtari",
      "source_ref": "OCAtari (Delfosse et al. 2024), ocatari/ram/<game>.py RAM-mode extractors",
      "extractor_func": "_detect_objects_asteroids_raw",
      "verified": false,
      "note": "RAM-mode extractor reference (no additive offset at use site)"
    },
    {
      "concept": "player_x",
      "ram_index": 73,
      "ram_addr_hex": "0xC9",
      "offset": null,
      "offset_applied": false,
      "raw": true,
      "is_slice": false,
      "slice_end": null,
      "source": "OCAtari",
      "source_ref": "OCAtari (Delfosse et al. 2024), ocatari/ram/<game>.py RAM-mode extractors",
      "extractor_func": "_detect_objects_asteroids_raw",
      "verified": false,
      "note": "RAM-mode extractor reference (no additive offset at use site)"
    },
    {
      "concept": "x",
      "ram_index": 73,
      "ram_addr_hex": "0xC9",
      "offset": null,
      "offset_applied": false,
      "raw": true,
      "is_slice": false,
      "slice_end": null,
      "source": "OCAtari",
      "source_ref": "OCAtari (Delfosse et al. 2024), ocatari/ram/<game>.py RAM-mode extractors",
      "extractor_func": "update_player",
      "verified": false,
      "note": "RAM-mode extractor reference (no additive offset at use site)"
    },
    {
      "concept": "player",
      "ram_index": 74,
      "ram_addr_hex": "0xCA",
      "offset": -41,
      "offset_applied": true,
      "raw": false,
      "is_slice": false,
      "slice_end": null,
      "source": "OCAtari",
      "source_ref": "OCAtari (Delfosse et al. 2024), ocatari/ram/<game>.py RAM-mode extractors",
      "extractor_func": "_augment_info_asteroids_ram",
      "verified": false,
      "note": "offset-corrected to rendered position"
    },
    {
      "concept": "player_y",
      "ram_index": 74,
      "ram_addr_hex": "0xCA",
      "offset": null,
      "offset_applied": false,
      "raw": true,
      "is_slice": false,
      "slice_end": null,
      "source": "OCAtari",
      "source_ref": "OCAtari (Delfosse et al. 2024), ocatari/ram/<game>.py RAM-mode extractors",
      "extractor_func": "_detect_objects_asteroids_raw",
      "verified": false,
      "note": "RAM-mode extractor reference (no additive offset at use site)"
    },
    {
      "concept": "y",
      "ram_index": 74,
      "ram_addr_hex": "0xCA",
      "offset": -41,
      "offset_applied": true,
      "raw": false,
      "is_slice": false,
      "slice_end": null,
      "source": "OCAtari",
      "source_ref": "OCAtari (Delfosse et al. 2024), ocatari/ram/<game>.py RAM-mode extractors",
      "extractor_func": "update_player",
      "verified": false,
      "note": "offset-corrected to rendered position"
    },
    {
      "concept": "diff_to_start_x",
      "ram_index": 77,
      "ram_addr_hex": "0xCD",
      "offset": null,
      "offset_applied": false,
      "raw": true,
      "is_slice": false,
      "slice_end": null,
      "source": "OCAtari",
      "source_ref": "OCAtari (Delfosse et al. 2024), ocatari/ram/<game>.py RAM-mode extractors",
      "extractor_func": "_detect_objects_asteroids_raw",
      "verified": false,
      "note": "RAM-mode extractor reference (no additive offset at use site)"
    },
    {
      "concept": "player",
      "ram_index": 77,
      "ram_addr_hex": "0xCD",
      "offset": null,
      "offset_applied": false,
      "raw": true,
      "is_slice": false,
      "slice_end": null,
      "source": "OCAtari",
      "source_ref": "OCAtari (Delfosse et al. 2024), ocatari/ram/<game>.py RAM-mode extractors",
      "extractor_func": "_augment_info_asteroids_ram",
      "verified": false,
      "note": "RAM-mode extractor reference (no additive offset at use site)"
    },
    {
      "concept": "player_missile_1_x",
      "ram_index": 83,
      "ram_addr_hex": "0xD3",
      "offset": null,
      "offset_applied": false,
      "raw": true,
      "is_slice": false,
      "slice_end": null,
      "source": "OCAtari",
      "source_ref": "OCAtari (Delfosse et al. 2024), ocatari/ram/<game>.py RAM-mode extractors",
      "extractor_func": "_detect_objects_asteroids_raw",
      "verified": false,
      "note": "RAM-mode extractor reference (no additive offset at use site)"
    },
    {
      "concept": "player_missile_2_x",
      "ram_index": 84,
      "ram_addr_hex": "0xD4",
      "offset": null,
      "offset_applied": false,
      "raw": true,
      "is_slice": false,
      "slice_end": null,
      "source": "OCAtari",
      "source_ref": "OCAtari (Delfosse et al. 2024), ocatari/ram/<game>.py RAM-mode extractors",
      "extractor_func": "_detect_objects_asteroids_raw",
      "verified": false,
      "note": "RAM-mode extractor reference (no additive offset at use site)"
    },
    {
      "concept": "player_missile_1_y",
      "ram_index": 86,
      "ram_addr_hex": "0xD6",
      "offset": null,
      "offset_applied": false,
      "raw": true,
      "is_slice": false,
      "slice_end": null,
      "source": "OCAtari",
      "source_ref": "OCAtari (Delfosse et al. 2024), ocatari/ram/<game>.py RAM-mode extractors",
      "extractor_func": "_detect_objects_asteroids_raw",
      "verified": false,
      "note": "RAM-mode extractor reference (no additive offset at use site)"
    },
    {
      "concept": "player_missile_2_y",
      "ram_index": 87,
      "ram_addr_hex": "0xD7",
      "offset": null,
      "offset_applied": false,
      "raw": true,
      "is_slice": false,
      "slice_end": null,
      "source": "OCAtari",
      "source_ref": "OCAtari (Delfosse et al. 2024), ocatari/ram/<game>.py RAM-mode extractors",
      "extractor_func": "_detect_objects_asteroids_raw",
      "verified": false,
      "note": "RAM-mode extractor reference (no additive offset at use site)"
    },
    {
      "concept": "player_missile_1_dir",
      "ram_index": 89,
      "ram_addr_hex": "0xD9",
      "offset": null,
      "offset_applied": false,
      "raw": true,
      "is_slice": false,
      "slice_end": null,
      "source": "OCAtari",
      "source_ref": "OCAtari (Delfosse et al. 2024), ocatari/ram/<game>.py RAM-mode extractors",
      "extractor_func": "_detect_objects_asteroids_raw",
      "verified": false,
      "note": "RAM-mode extractor reference (no additive offset at use site)"
    },
    {
      "concept": "player_missile_2_dir",
      "ram_index": 90,
      "ram_addr_hex": "0xDA",
      "offset": null,
      "offset_applied": false,
      "raw": true,
      "is_slice": false,
      "slice_end": null,
      "source": "OCAtari",
      "source_ref": "OCAtari (Delfosse et al. 2024), ocatari/ram/<game>.py RAM-mode extractors",
      "extractor_func": "_detect_objects_asteroids_raw",
      "verified": false,
      "note": "RAM-mode extractor reference (no additive offset at use site)"
    }
  ]
}
